qiskit_quantum_knn/__init__.py
qiskit_quantum_knn/encoding/__init__.py
qiskit_quantum_knn/encoding/analog.py
qiskit_quantum_knn/qknn/__init__.py
qiskit_quantum_knn/qknn/_qknn.py
qiskit_quantum_knn/qknn/qkneighborsclassifier.py
qiskit_quantum_knn/qknn/qknn_construction.py
qiskit_quantum_knn/qknn/quantumgates.py
qiskit_quantum_knn-1.0.1.dist-info/LICENSE
qiskit_quantum_knn-1.0.1.dist-info/METADATA
qiskit_quantum_knn-1.0.1.dist-info/WHEEL
qiskit_quantum_knn-1.0.1.dist-info/top_level.txt
qiskit_quantum_knn-1.0.1.dist-info/RECORD
