Metadata-Version: 2.1
Name: qiskit-quantum-knn
Version: 1.0.1
Summary: UNKNOWN
Home-page: https://github.com/GroenteLepel/qiskit-quantum-knn
Author: Daniel J. Kok
Author-email: djkok.github@icloud.com
License: UNKNOWN
Platform: UNKNOWN
Classifier: Development Status :: 3 - Alpha
Classifier: Environment :: Console
Classifier: Intended Audience :: Science/Research
Classifier: License :: OSI Approved :: Apache Software License
Classifier: Operating System :: Unix
Classifier: Programming Language :: Python :: 3.8
Classifier: Topic :: Scientific/Engineering :: Physics
Requires-Python: >=3.6
Requires-Dist: numpy
Requires-Dist: scipy
Requires-Dist: qiskit
Provides-Extra: visualization
Requires-Dist: matplotlib (>=2.1) ; extra == 'visualization'
Requires-Dist: ipywidgets (>=7.3.0) ; extra == 'visualization'
Requires-Dist: pydot ; extra == 'visualization'
Requires-Dist: pillow (>=4.2.1) ; extra == 'visualization'
Requires-Dist: pylatexenc (>=1.4) ; extra == 'visualization'
Requires-Dist: seaborn (>=0.9.0) ; extra == 'visualization'
Requires-Dist: pygments (>=2.4) ; extra == 'visualization'
